util_py/./.git
util_py/./.gitignore
util_py/./LICENSE
util_py/./README.en.md
util_py/./README.md
util_py/./__about__.py
util_py/./__init__.py
util_py/./array.py
util_py/./dd.py
util_py/./dt.py
util_py/./echart.py
util_py/./encrypt.py
util_py/./fs.py
util_py/./log.py
util_py/./os.py
util_py/./pyproject.toml
util_py/./requirements.txt
util_py/./security.py
util_py/./vika.py
util_td-0.0.13.dist-info/METADATA
util_td-0.0.13.dist-info/WHEEL
util_td-0.0.13.dist-info/licenses/LICENSE
util_td-0.0.13.dist-info/RECORD
