Metadata-Version: 2.3
Name: util_td
Version: 0.0.13
License-Expression: MIT
License-File: LICENSE
Requires-Python: >=3.8
Requires-Dist: multitasking==0.0.11
Requires-Dist: python-dateutil==2.9.*
Requires-Dist: vika==1.3.1
